{
  "name": "sql",
  "scopeName": "source.sql",
  "fileTypes": [
    ".sql"
  ],
  "patterns": [
    {
      "include": "#comments"
    },
    {
      "name": "keyword.control.sql",
      "match": "\\b([aA][sS]|[cC][rR][eE][aA][tT][eE]|[fF][rR][oO][mM]|[jJ][oO][iI][nN]|[oO][nN]|[sS][eE][lL][eE][cC][tT]|[tT][aA][bB][lL][eE]|[tT][yY][pP][eE])\\b"
    }
  ],
  "repository": {
    "comments": {
      "patterns": [
        {
          "name": "comment.block.sql",
          "begin": "/\\*",
          "beginCaptures": {
            "0": {
              "name": "punctuation.definition.comment.sql"
            }
          },
          "end": "\\*/",
          "endCaptures": {
            "0": {
              "name": "punctuation.definition.comment.sql"
            }
          }
        },
        {
          "begin": "//",
          "beginCaptures": {
            "1": {
              "name": "punctuation.whitespace.comment.leading.sql"
            }
          },
          "end": "(?=$)",
          "name": "comment.line.sql"
        }
      ]
    }
  }
}